kirakoai/__init__.py
kirakoai/client.py
kirakoai/exceptions.py
kirakoai/models.py
kirakoai-0.1.1.dist-info/METADATA
kirakoai-0.1.1.dist-info/WHEEL
kirakoai-0.1.1.dist-info/top_level.txt
kirakoai-0.1.1.dist-info/RECORD
