Metadata-Version: 2.4
Name: kirakoai
Version: 0.1.1
Summary: KirakoAI — продвинутый ИИ-помощник
Author-email: "kirako.ai" <help@kirako.ai>
Requires-Python: >=3.8
Requires-Dist: requests>=2.31.0
Requires-Dist: pydantic>=2.0.0
